friendli_gradio/__init__.py
friendli_gradio/utils/token_loader.py
friendli_gradio-0.0.5.dist-info/METADATA
friendli_gradio-0.0.5.dist-info/WHEEL
friendli_gradio-0.0.5.dist-info/RECORD
