Metadata-Version: 2.4
Name: friendli-gradio
Version: 0.0.5
Summary: A Python package for creating Gradio applications with Friendli serverless models
Project-URL: homepage, https://github.com/friendliai/friendli-gradio
Project-URL: repository, https://github.com/friendliai/friendli-gradio
Author-email: minpeter <minpeter@friendli.ai>
Classifier: License :: OSI Approved :: MIT License
Classifier: Operating System :: OS Independent
Classifier: Programming Language :: Python :: 3
Requires-Python: >=3.10
Requires-Dist: gradio>=5.5.0
Requires-Dist: keyring>=25.6.0
Requires-Dist: openai>=1.99.1
Requires-Dist: python-dotenv
Provides-Extra: dev
Requires-Dist: pytest; extra == 'dev'
